telegrinder_templating/__init__.py
telegrinder_templating/abc.py
telegrinder_templating/jinja.py
telegrinder_templating-1.0.4.dist-info/LICENSE
telegrinder_templating-1.0.4.dist-info/METADATA
telegrinder_templating-1.0.4.dist-info/WHEEL
telegrinder_templating-1.0.4.dist-info/RECORD
