Metadata-Version: 2.1
Name: telegrinder-templating
Version: 1.0.4
Summary: This module is used with telegrinder framework. It is used to create text templates.
Home-page: https://github.com/luwqz1/telegrinder_templating
License: MIT
Keywords: python,telegrinder framework,tool,templating,telegrinder tool,jinja2
Author: Geogry howl
Author-email: howluwqz1@gmail.com
Requires-Python: >=3.11,<4.0
Classifier: Framework :: AsyncIO
Classifier: Intended Audience :: Developers
Classifier: Intended Audience :: Information Technology
Classifier: Intended Audience :: System Administrators
Classifier: License :: OSI Approved :: MIT License
Classifier: Programming Language :: Python :: 3
Classifier: Programming Language :: Python :: 3.11
Classifier: Programming Language :: Python :: 3 :: Only
Classifier: Programming Language :: Python :: 3.11
Classifier: Programming Language :: Python :: Implementation :: PyPy
Classifier: Topic :: Communications :: Chat
Classifier: Topic :: Internet
Classifier: Topic :: Software Development :: Libraries :: Python Modules
Requires-Dist: jinja2 (>=3.1.2,<4.0.0)
Project-URL: Repository, https://github.com/luwqz1/telegrinder_templating
